Metadata-Version: 2.4
Name: computer-control-mcp-lands
Version: 0.0.3
Summary: MCP server that provides computer control capabilities, like mouse, keyboard, OCR, etc. using PyAutoGUI, RapidOCR, ONNXRuntime. Similar to 'computer-use' by Anthropic. With Zero External Dependencies.
Project-URL: Homepage, https://github.com/songcaiya/computer-control-mcp-lands
Author-email: lands <1158232449@qq.com>
License: MIT
License-File: LICENSE
Classifier: Development Status :: 4 - Beta
Classifier: Intended Audience :: Developers
Classifier: License :: OSI Approved :: MIT License
Classifier: Programming Language :: Python :: 3
Classifier: Programming Language :: Python :: 3.12
Classifier: Topic :: Software Development :: Libraries
Classifier: Topic :: Utilities
Requires-Python: >=3.12
Requires-Dist: fuzzywuzzy
Requires-Dist: mcp[cli]
Requires-Dist: onnxruntime
Requires-Dist: opencv-python
Requires-Dist: pillow
Requires-Dist: pyautogui
Requires-Dist: pygetwindow
Requires-Dist: rapidocr
Requires-Dist: rapidocr-onnxruntime==1.2.3
